ciscoconfaudit/__init__.py
ciscoconfaudit-0.1.2.dist-info/LICENSE
ciscoconfaudit-0.1.2.dist-info/METADATA
ciscoconfaudit-0.1.2.dist-info/NOTICE
ciscoconfaudit-0.1.2.dist-info/WHEEL
ciscoconfaudit-0.1.2.dist-info/top_level.txt
ciscoconfaudit-0.1.2.dist-info/RECORD
