Metadata-Version: 2.1
Name: ciscoconfaudit
Version: 0.1.2
Summary: A Cisco IOS & IOS-XE configuration audit tool
Author-email: Osama Abbas <oabbas2512@gmail.com>
Maintainer-email: Osama Abbas <oabbas2512@gmail.com>
License: GNU GENERAL PUBLIC LICENSE
Project-URL: Homepage, https://github.com/Tes3awy/cisco-config-auditor/
Project-URL: Bug Tracker, https://github.com/Tes3awy/cisco-config-auditor/issues/
Project-URL: Say Thanks!, https://saythanks.io/to/Tes3awy
Project-URL: Source, https://github.com/Tes3awy/cisco-config-auditor/
Keywords: cisco,audit,configuration audit
Classifier: Development Status :: 5 - Production/Stable
Classifier: Environment :: Console
Classifier: Intended Audience :: Developers
Classifier: Intended Audience :: System Administrators
Classifier: Topic :: Software Development :: Libraries :: Python Modules
Classifier: Topic :: Software Development :: Quality Assurance
Classifier: Topic :: System :: Networking :: Monitoring
Classifier: Topic :: System :: Systems Administration
Classifier: License :: OSI Approved :: GNU General Public License (GPL)
Classifier: Natural Language :: English
Classifier: Operating System :: OS Independent
Classifier: Programming Language :: Python :: 3 :: Only
Classifier: Programming Language :: Python :: 3.8
Classifier: Programming Language :: Python :: 3.9
Classifier: Programming Language :: Python :: 3.10
Classifier: Programming Language :: Python :: 3.11
Classifier: Programming Language :: Python :: 3.12
Requires-Python: >=3.8
License-File: LICENSE
License-File: NOTICE
Requires-Dist: ciscoconfparse
Requires-Dist: rich
Provides-Extra: dev
Requires-Dist: pre-commit ; extra == 'dev'
Requires-Dist: black ; extra == 'dev'
Requires-Dist: isort ; extra == 'dev'
